pyramid_tasks/__init__.py
pyramid_tasks/celery.py
pyramid_tasks/events.py
pyramid_tasks/interfaces.py
pyramid_tasks/settings.py
pyramid_tasks/taskderivers.py
pyramid_tasks/transaction.py
pyramid_tasks/contrib/__init__.py
pyramid_tasks/contrib/pyramid_tm.py
pyramid_tasks-0.4.0.dist-info/licenses/LICENSE
pyramid_tasks-0.4.0.dist-info/METADATA
pyramid_tasks-0.4.0.dist-info/WHEEL
pyramid_tasks-0.4.0.dist-info/top_level.txt
pyramid_tasks-0.4.0.dist-info/RECORD
