Metadata-Version: 2.4
Name: pyramid-tasks
Version: 0.4.0
Summary: Bring parity to Pyramid and Celery by creating a full Pyramid application in the Celery worker and providing a request object for each task.
Author-email: Theron Luhn <theron@luhn.com>
License-Expression: MIT
Project-URL: Homepage, https://github.com/luhn/pyramid-tasks/
Project-URL: Documentation, https://github.com/luhn/pyramid-tasks/
Project-URL: Repository, https://github.com/luhn/pyramid-tasks/
Project-URL: Issues, https://github.com/luhn/pyramid-tasks/issues
Project-URL: Changelog, https://github.com/luhn/pyramid-tasks/releases
Classifier: Development Status :: 4 - Beta
Classifier: Framework :: Pyramid
Classifier: Framework :: Celery
Classifier: Intended Audience :: Developers
Classifier: Operating System :: OS Independent
Classifier: Programming Language :: Python :: 3 :: Only
Classifier: Programming Language :: Python :: 3
Classifier: Programming Language :: Python :: 3.9
Classifier: Programming Language :: Python :: 3.10
Classifier: Programming Language :: Python :: 3.11
Classifier: Programming Language :: Python :: 3.12
Classifier: Programming Language :: Python :: 3.13
Classifier: Programming Language :: Python :: Implementation :: CPython
Classifier: Programming Language :: Python :: Implementation :: PyPy
Classifier: Programming Language :: Python
Requires-Python: >=3.9
License-File: LICENSE
Requires-Dist: celery<6,>=4
Requires-Dist: pyramid>=1.9
Requires-Dist: venusian>=1.0
Requires-Dist: zope.interface>=3.8.0
Provides-Extra: testing
Requires-Dist: pyramid-tm~=2.4; extra == "testing"
Requires-Dist: pytest~=8.3; extra == "testing"
Requires-Dist: sqlalchemy~=2.0; extra == "testing"
Requires-Dist: transaction~=5.0; extra == "testing"
Requires-Dist: zope.sqlalchemy~=3.1; extra == "testing"
Provides-Extra: linting
Requires-Dist: ruff~=0.13.0; extra == "linting"
Dynamic: license-file
